pkgLavanya/__init__.py
pkgLavanya/config.py
pkgLavanya/data.txt
pkgLavanya/detect_info.py
pkgLavanya/test_detect.py
pkgLavanya-0.1.14.dist-info/METADATA
pkgLavanya-0.1.14.dist-info/WHEEL
pkgLavanya-0.1.14.dist-info/top_level.txt
pkgLavanya-0.1.14.dist-info/RECORD
