Metadata-Version: 2.1
Name: pkgLavanya
Version: 0.1.14
Summary: utility package designed to detect sensitive 
Author: Lavanya
Author-email: lavanya.narang@dataverze.ai
Classifier: Programming Language :: Python :: 3
Classifier: License :: OSI Approved :: MIT License
Classifier: Operating System :: OS Independent
Requires-Python: >=3.7
Requires-Dist: pytest
Requires-Dist: pylance
Requires-Dist: pip
Requires-Dist: python
